<podcast>
	TWiV
	<episode>
		622: Nonhuman primate model for COVID-19 with Emmie de Wit
		<meta>
			*
			<links>
				<link>
					*
				</link>
				<link>
					*
				</link>
				<link>
					*
				</link>
				<link>					
					*
				</link>
				<link>					
					*
				</link>
				<link>	
					*
				</link>
				<link>	
					*
				</link>
			</links>
		<time>
			00:00:00
			<tag>
				x 
			</tag>
			<description>
				x
			</description>
		</time>	
		<time>
			00:02:00
			<tag>
				x 
			</tag>
			<description>
				x
			</description>
		</time>
		<time>
			00:03:00
			<tag>
				x 
			</tag>
			<description>
				x
			</description>
		</time>		
		<time>
			00:06:00
			<tag>
				x 
			</tag>
			<description>
				x
			</description>
		</time>	
		<time>
			00:09:00
			<tag>
				x 
			</tag>
			<description>
				x
			</description>
		</time>
		<time>
			00:11:00
			<tag>
				x 
			</tag>
			<description>
				x
			</description>
		</time>	
		<time>
			00:12:00
			<tag>
				x 
			</tag>
			<description>
				x
			</description>
		</time>	
		<time>
			00:15:00
			<tag>
				x 
			</tag>
			<description>
				x
			</description>
		</time>
		<time>
			00:16:00
			<tag>
				x 
			</tag>
			<description>
				x
			</description>
		</time>	
		<time>
			00:20:00
			<tag>
				x 
			</tag>
			<description>
				x
			</description>
		</time>	
		<time>
			00:22:00
			<tag>
				x 
			</tag>
			<description>
				x
			</description>
		</time>
		<time>
			00:23:00
			<tag>
				x 
			</tag>
			<description>
				x
			</description>
		</time>	
		<time>
			00:25:00
			<tag>
				x 
			</tag>
			<description>
				x
			</description>
		</time>	
		<time>
			00:26:00
			<tag>
				x 
			</tag>
			<description>
				x
			</description>
		</time>
		<time>
			00:29:00
			<tag>
				x 
			</tag>
			<description>
				x
			</description>
		</time>	
		<time>
			00:30:00
			<tag>
				x 
			</tag>
			<description>
				x
			</description>
		</time>	
		<time>
			00:32:00
			<tag>
				x 
			</tag>
			<description>
				x
			</description>
		</time>
		<time>
			00:33:00
			<tag>
				x 
			</tag>
			<description>
				x
			</description>
		</time>	
		<time>
			00:34:00
			<tag>
				x 
			</tag>
			<description>
				x
			</description>
		</time>	
		<time>
			00:36:00
			<tag>
				x 
			</tag>
			<description>
				x
			</description>
		</time>
		<time>
			00:37:00
			<tag>
				x 
			</tag>
			<description>
				x
			</description>
		</time>	
		<time>
			00:38:00
			<tag>
				x 
			</tag>
			<description>
				Cell culture not sensivtive
			</description>
		</time>	
		<time>
			00:39:00
			<tag>
				x 
			</tag>
			<description>
				x
			</description>
		</time>
		<time>
			00:40:00
			<tag>
				x 
			</tag>
			<description>
				x
			</description>
		</time>	
		<time>
			00:41:00
			<tag>
				x 
			</tag>
			<description>
				x
			</description>
		</time>	
		<time>
			00:43:00
			<tag>
				x 
			</tag>
			<description>
				x
			</description>
		</time>
		<time>
			00:43:00
			<tag>
				x 
			</tag>
			<description>
				x
			</description>
		</time>	
		<time>
			00:48:00
			<tag>
				x 
			</tag>
			<description>
				x
			</description>
		</time>	
		<time>
			00:50:00
			<tag>
				x 
			</tag>
			<description>
				x
			</description>
		</time>
				<time>
			00:53:00
			<tag>
				x 
			</tag>
			<description>
				x
			</description>
		</time>	
		<time>
			00:55:00
			<tag>
				x 
			</tag>
			<description>
				x
			</description>
		</time>
		<time>
			00:58:00
			<tag>
				x 
			</tag>
			<description>
				x
			</description>
		</time>	
		<time>
			00:59:00
			<tag>
				x 
			</tag>
			<description>
				x
			</description>
		</time>	
		<time>
			01:00:00
			<tag>
				x 
			</tag>
			<description>
				x
			</description>
		</time>	
		<time>
			01:02:00
			<tag>
				x 
			</tag>
			<description>
				x
			</description>
		</time>
			<time>
				01:03:00
				<tag>
					x 
				</tag>
				<description>
					x
				</description>
			</time>	
			<time>
				01:04:00
				<tag>
					x 
				</tag>
				<description>
					x
				</description>
				</time>	
			<time>
				01:05:00
				<tag>
					x 
				</tag>
				<description>
					NIH Hamiton Rokey Mountain Lab 
				</description>
			</time>
			<time>
				00:00:00
				<tag>
					x 
				</tag>
				<description>
					x
				</description>
			</time>
		</meta>
	</episode>	
	<episode>
		623: Bats and coronaviruses with Peter Daszak
		<meta>
			Vincent Racaniello, Rich Condit, Kathy Spindler, Brianne Barker, Peter Daszak
			<links>
				<link>
					Bats are reservoirs of SARSr-CoV (Science) 3:40
				</link>
				<link>
					Bat SARSr-CoV that binds ACE2 (Nature) 22:07
				</link>
				<link>
					Rich gene pool of bat SARSr-CoV (PLoS Path) 30:30
				</link>
				<link>					
					Bat SARSr-CoV infect humans (Virol Sin) 33:18
				</link>
				<link>					
					Transmission of bat SARSr-CoV in China (bioRxiv) 45:17
				</link>
				<link>	
					Global Virome Project (Science) 47:32, 55:15
				</link>
				<link>	
					ASV Virtual Workshops 2020 1:18:57
				</link>
			</links>
			<time>
				00:02:00
				<tag>
					x 
				</tag>
				<description>
					x
				</description>
			</time>
			<time>
				00:03:00
				<tag>
					x 
				</tag>
				<description>
					x
				</description>
			</time>
			<time>
				00:06:00
				<tag>
					x 
				</tag>
				<description>
					x
				</description>
			</time>
			<time>
				00:07:00
				<tag>
					x 
				</tag>
				<description>
					x
				</description>
			</time>
			<time>
				00:09:00
				<tag>
					x 
				</tag>
				<description>
					x
				</description>
			</time>
			<time>
				00:09:00
				<tag>
					x 
				</tag>
				<description>
					x
				</description>
			</time>
			<time>
				00:12:00
				<tag>
					x 
				</tag>
				<description>
					x
				</description>
			</time>
			<time>
				00:17:00
				<tag>
					x 
				</tag>
				<description>
					x
				</description>
			</time>
			<time>
				00:19:00
				<tag>
					x 
				</tag>
				<description>
					x
				</description>
			</time>
			<time>
				00:20:00
				<tag>
					x 
				</tag>
				<description>
					x
				</description>
			</time>
			<time>
				00:21:00
				<tag>
					x 
				</tag>
				<description>
					x
				</description>
			</time>
			<time>
				00:25:00
				<tag>
					x 
				</tag>
				<description>
					x
				</description>
			</time>
			<time>
				00:28:00
				<tag>
					x 
				</tag>
				<description>
					x
				</description>
			</time>
			<time>
				00:30:30
				<tag>
					Vincent Racaniello, Peter Daszak
				</tag>
				<description>
					Paper a few years ago Descovery of a new gene pool, Jun Lee finding virus
				</description>
			</time>
			<time>
				00:32:00
				<tag>
					Peter Daszak
				</tag>
				<description>
					Targeting what is missing, 30% diferent from SARS-1 maybe able to infect human cells
				</description>
			</time>
			<time>
				00:34:30
				<tag>
					x 
				</tag>
				<description>
					3% prevalence will infect 1 to 7 million people in South East Asia each year
				</description>
			</time>
			<time>
				00:37:00
				<tag>
					x 
				</tag>
				<description>
					x
				</description>
			</time>
			<time>
				00:38:00
				<tag>
					x 
				</tag>
				<description>
					x
				</description>
			</time>
			<time>
				00:40:00
				<tag>
					x 
				</tag>
				<description>
					x
				</description>
			</time>
			<time>
				00:42:00
				<tag>
					x 
				</tag>
				<description>
					x
				</description>
			</time>
			<time>
				00:43:00
				<tag>
					x 
				</tag>
				<description>
					x
				</description>
			</time>
			<time>
				00:45:00
				<tag>
					x 
				</tag>
				<description>
					x
				</description>
			</time>
			<time>
				00:48:00
				<tag>
					x 
				</tag>
				<description>
					x
				</description>
			</time>
			<time>
				00:49:00
				<tag>
					x 
				</tag>
				<description>
					x
				</description>
			</time>
			<time>
				00:50:00
				<tag>
					x 
				</tag>
				<description>
					x
				</description>
			</time>
			<time>
				00:51:00
				<tag>
					x 
				</tag>
				<description>
					x
				</description>
			</time>
			<time>
				00:52:00
				<tag>
					x 
				</tag>
				<description>
					x
				</description>
			</time>
			<time>
				00:53:00
				<tag>
					x 
				</tag>
				<description>
					x
				</description>
			</time>
			<time>
				00:54:00
				<tag>
					x 
				</tag>
				<description>
					x
				</description>
			</time>
			<time>
				00:56:00
				<tag>
					x 
				</tag>
				<description>
					x
				</description>
			</time>
			<time>
				01:04:00
				<tag>
					x 
				</tag>
				<description>
					x
				</description>
			</time>
			<time>
				01:06:19
				<tag>
					Vincent Racaniello, Peter Daszak
				</tag>
				<description>
					Why was your money withdrawn? Wuhan Lab, Can't prove a negative.
				</description>
			</time>
			<time>
				01:08:56
				<tag>
					Rich Condit
				</tag>
				<description>
					Sicentfic push back, Eco Allience not going to the press
				</description>
			</time>
			<time>
				01:10:45
				<tag>
					Peter Daszak
				</tag>
				<description>
					Notice of Award
				</description>
			</time>
			<time>
				01:11:40
				<tag>
					Peter Daszak
				</tag>
				<description>
					Doing the work voluntary to find the origin of the virus
				</description>
			</time>
			<time>
				01:12:15
				<tag>
					Vincent Racaniello, Peter Daszak
				</tag>
				<description>
					Is it possiblie that other countres will step in. We have 16000 bat samples in China
				</description>
			</time>
			<time>
				01:13:30
				<tag>
					Vincent Racaniello, Peter Daszak
				</tag>
				<description>
					 Hopefully after a change of administration thigs will change
				</description>
			</time>
			<time>
				01:15:00
				<tag>
					Brianne Barker, Peter Daszak
				</tag>
				<description>
					Makes me angree that we have samples in China we can't work with, Two golbal super powers and this is an election issue
				</description>
			</time>
			<time>
				01:15:55
				<tag>
					Peter Daszak
				</tag>
				<description>
					781 sequences for bat coronaviruses any one could be the next pandemic
				</description>
			</time>
			<time>
				01:17:55
				<tag>
					Peter Daszak
				</tag>
				<description>
					Get people out there to prove ths is natual 
				</description>
			</time>			
		</meta>
	</epiosode>	
	<episode>
		624: SeXX matters with Sabra Klein
		<meta>
			*
			<links>
				<link>
					*
				</link>
				<link>
					*
				</link>
				<link>
					*
				</link>
				<link>					
					*
				</link>
				<link>					
					*
				</link>
				<link>	
					*
				</link>
				<link>	
					*
				</link>
			</links>
			<time>
				00:00:00
				<tag>
					x 
				</tag>
				<description>
					x
				</description>
			</time>
		</meta>
	</episode>	
	<episode>
		625: Fred Murphy, virologist for all seasons
		<meta>
			*
			<links>
				<link>
					*
				</link>
				<link>
					*
				</link>
				<link>
					*
				</link>
				<link>					
					*
				</link>
				<link>					
					*
				</link>
				<link>	
					*
				</link>
				<link>	
					*
				</link>
			</links>
			<time>
				00:00:00
				<tag>
					x 
				</tag>
				<description>
					x
				</description>
			</time>
		</meta>
	</episode>	
	<episode>
		626: Ralph Baric and fancy ferrets
		<meta>
			12062020, 14062020, Vincent Racaniello, Dickson Despommier, Alan Dove, Rich Condit, Brianne Barker, Daniel Griffin, Chuck Knirsch, Ralph Baric
			<links>
				<link>
					*
				</link>
				<link>
					*
				</link>
				<link>
					*
				</link>
				<link>					
					*
				</link>
				<link>					
					*
				</link>
				<link>	
					*
				</link>
				<link>	
					*
				</link>
			</links>
			<time>
				00:00:50
				<tag>
					Daniel Griffin
				</tag>
				<description>
					Need sleep
				</description>
			</time>			
			<time>
				00:01:30
				<tag>
					Daniel Griffin
				</tag>
				<description>
					PBS frontline
				</description>
			</time>	
			<time>
				00:02:00
				<tag>
					Daniel Griffin
				</tag>
				<description>
					Observations v data
				</description>
			</time>				
			<time>
				00:03:45
				<tag>
					Daniel Griffin 
				</tag>
				<description>
					Difference based on race, Black Americans 61 White Americans 22 per 100000 deaths.
				</description>
			</time>			
			<time>
				00:05:11
				<tag>
					Daniel Griffin 
				</tag>
				<description>
					Dying a twice the population share
				</description>
			</time>			
			<time>
				00:06:30
				<tag>
					Daniel Griffin, Vincent Racaniello
				</tag>
				<description>
					Why is this effecting different races differently
				</description>
			</time>			
			<time>
				00:07:50
				<tag>
					Daniel Griffin
				</tag>
				<description>
					Paracites without boarders work
				</description>
			</time>			
			<time>
				00:09:30
				<tag>
					Daniel Griffin
				</tag>
				<description>
					Mask wearing being seen
				</description>
			</time>			
			<time>
				00:10:00
				<tag>
					Daniel Griffin, Chuck Knirsch
				</tag>
				<description>
					Not doing well in Arizona, Africa, Kenya
				</description>
			</time>			
			<time>
				00:11:00
				<tag>
					x 
				</tag>
				<description>
					x
				</description>
			</time>			
			<time>
				00:12:00
				<tag>
					x 
				</tag>
				<description>
					x
				</description>
			</time>			
			<time>
				00:15:00
				<tag>
					x 
				</tag>
				<description>
					x
				</description>
			</time>			
			<time>
				00:18:00
				<tag>
					x 
				</tag>
				<description>
					x
				</description>
			</time>			
			<time>
				00:19:00
				<tag>
					Daniel Griffin
				</tag>
				<description>
					Masks data that will reduce the R rate for good well worn masks, more infection if not worn well, masks stop droplets
				</description>
			</time>			
			<time>
				00:22:10
				<tag>
					Daniel Griffin
				</tag>
				<description>
					PCR issues to sort out
				</description>
			</time>			
			<time>
				00:22:45
				<tag>
					Daniel Griffin 
				</tag>
				<description>
					Serology testing
				</description>
			</time>			
			<time>
				00:24:20
				<tag>
					Vincent Racaniello, Daniel Griffin
				</tag>
				<description>
					2 tests better than 1
				</description>
			</time>	
			<time>
				00:29:00
				<tag>
					x 
				</tag>
				<description>
					x
				</description>
			</time>			
			<time>
				00:29:00
				<tag>
					x 
				</tag>
				<description>
					x
				</description>
			</time>			
			<time>
				00:30:00
				<tag>
					x 
				</tag>
				<description>
					x
				</description>
			</time>	
			<time>
				00:32:00
				<tag>
					x 
				</tag>
				<description>
					x
				</description>
			</time>
			<time>
				00:34:00
				<tag>
					x 
				</tag>
				<description>
					x
				</description>
			</time>
			<time>
				00:36:00
				<tag>
					x 
				</tag>
				<description>
					x
				</description>
			</time>
			<time>
				00:41:00
				<tag>
					x 
				</tag>
				<description>
					x
				</description>
			</time>
			<time>
				00:42:00
				<tag>
					x 
				</tag>
				<description>
					x
				</description>
			</time>
			<time>
				00:44:00
				<tag>
					x 
				</tag>
				<description>
					x
				</description>
			</time>
			<time>
				00:45:00
				<tag>
					x 
				</tag>
				<description>
					x
				</description>
			</time>
			<time>
				00:46:00
				<tag>
					x 
				</tag>
				<description>
					x
				</description>
			</time>
			<time>
				00:47:00
				<tag>
					x 
				</tag>
				<description>
					x
				</description>
			</time>
			<time>
				00:54:00
				<tag>
					x 
				</tag>
				<description>
					x
				</description>
			</time>
			<time>
				00:55:00
				<tag>
					x 
				</tag>
				<description>
					x
				</description>
			</time>
			<time>
				00:57:00
				<tag>
					x 
				</tag>
				<description>
					x
				</description>
			</time>
			<time>
				00:59:00
				<tag>
					x 
				</tag>
				<description>
					x
				</description>
			</time>
			<time>
				01:00:00
				<tag>
					x 
				</tag>
				<description>
					x
				</description>
			</time>
			<time>
				01:01:00
				<tag>
					x 
				</tag>
				<description>
					x
				</description>
			</time>	
			<time>
				01:02:00
				<tag>
					x 
				</tag>
				<description>
					x
				</description>
			</time>	
			<time>
				01:04:00
				<tag>
					x 
				</tag>
				<description>
					x
				</description>
			</time>	
			<time>
				01:05:00
				<tag>
					x 
				</tag>
				<description>
					x
				</description>
			</time>	
			<time>
				01:07:00
				<tag>
					x 
				</tag>
				<description>
					x
				</description>
			</time>	
			<time>
				01:09:00
				<tag>
					x 
				</tag>
				<description>
					x
				</description>
			</time>	
			<time>
				01:11:00
				<tag>
					x 
				</tag>
				<description>
					x
				</description>
			</time>	
			<time>
				01:01:00
				<tag>
					x 
				</tag>
				<description>
					x
				</description>
			</time>	
			<time>
				01:12:00
				<tag>
					x 
				</tag>
				<description>
					x
				</description>
			</time>	
			<time>
				01:14:00
				<tag>
					x 
				</tag>
				<description>
					x
				</description>
			</time>	
			<time>
				01:16:00
				<tag>
					x 
				</tag>
				<description>
					x
				</description>
			</time>	
			<time>
				01:17:00
				<tag>
					x 
				</tag>
				<description>
					x
				</description>
			</time>	
			<time>
				01:19:00
				<tag>
					x 
				</tag>
				<description>
					x
				</description>
			</time>	
			<time>
				01:20:00
				<tag>
					x 
				</tag>
				<description>
					x
				</description>
			</time>	
			<time>
				01:21:00
				<tag>
					x 
				</tag>
				<description>
					x
				</description>
			</time>	
			<time>
				01:22:00
				<tag>
					x 
				</tag>
				<description>
					x
				</description>
			</time>	
			<time>
				01:23:00
				<tag>
					x 
				</tag>
				<description>
					x
				</description>
			</time>	
			<time>
				01:25:00
				<tag>
					x 
				</tag>
				<description>
					x
				</description>
			</time>	
			<time>
				01:27:00
				<tag>
					x 
				</tag>
				<description>
					x
				</description>
			</time>	
			<time>
				01:28:00
				<tag>
					x 
				</tag>
				<description>
					x
				</description>
			</time>	
			<time>
				01:30:00
				<tag>
					x 
				</tag>
				<description>
					x
				</description>
			</time>	
			<time>
				01:31:00
				<tag>
					x 
				</tag>
				<description>
					x
				</description>
			</time>	
			<time>
				01:34:00
				<tag>
					x 
				</tag>
				<description>
					x
				</description>
			</time>	
			<time>
				01:35:00
				<tag>
					x 
				</tag>
				<description>
					x
				</description>
			</time>	
			<time>
				01:38:00
				<tag>
					x 
				</tag>
				<description>
					x
				</description>
			</time>	
			<time>
				01:39:00
				<tag>
					x 
				</tag>
				<description>
					x
				</description>
			</time>	
			<time>
				01:41:00
				<tag>
					x 
				</tag>
				<description>
					x
				</description>
			</time>	
			<time>
				01:42:00
				<tag>
					x 
				</tag>
				<description>
					x
				</description>
			</time>	
			<time>
				01:44:00
				<tag>
					x 
				</tag>
				<description>
					x
				</description>
			</time>	
			<time>
				01:48:00
				<tag>
					x 
				</tag>
				<description>
					x
				</description>
			</time>					
			<time>
				01:50:00
				<tag>
					Email, Brianne Barker, Vitamin D
				</tag>
				<description>
					Back people being more vulnerable to SARS-CoV-2 due to vitamin D deficiency. You are prised for taking this argument down.
				</description>
			</time>
			<time>
				01:54:00
				<tag>
					x 
				</tag>
				<description>
					x
				</description>
			</time>				
			<time>
				01:56:00
				<tag>
					x 
				</tag>
				<description>
					x
				</description>
			</time>				
			<time>
				01:56:00
				<tag>
					x 
				</tag>
				<description>
					x
				</description>
			</time>				
			<time>
				01:58:00
				<tag>
					x 
				</tag>
				<description>
					x
				</description>
			</time>				
			<time>
				02:00:00
				<tag>
					x 
				</tag>
				<description>
					x
				</description>
			</time>				
			<time>
				02:01:00
				<tag>
					x 
				</tag>
				<description>
					x
				</description>
			</time>				
			<time>
				02:02:00
				<tag>
					x 
				</tag>
				<description>
					x
				</description>
			</time>				
			<time>
				02:04:00
				<tag>
					x 
				</tag>
				<description>
					x
				</description>
			</time>				
			<time>
				02:06:00
				<tag>
					x 
				</tag>
				<description>
					x
				</description>
			</time>				
			<time>
				02:08:00
				<tag>
					x 
				</tag>
				<description>
					x
				</description>
			</time>				
			<time>
				02:09:00
				<tag>
					x 
				</tag>
				<description>
					x
				</description>
			</time>				
			<time>
				02:12:00
				<tag>
					x 
				</tag>
				<description>
					x
				</description>
			</time>	
			<time>
				02:17:00
				<tag>
					x 
				</tag>
				<description>
					x
				</description>
			</time>	
			<time>
				02:18:00
				<tag>
					x 
				</tag>
				<description>
					x
				</description>
			</time>	
			<time>
				02:22:00
				<tag>
					x 
				</tag>
				<description>
					x
				</description>
			</time>	
			<time>
				02:24:00
				<tag>
					x 
				</tag>
				<description>
					x
				</description>
			</time>				
			<time>
				02:27:45
				<tag>
					Alan Dove, WHO Asymtomatic
				</tag>
				<description>
					Statment that asymtomatic spread is not a significant factor.
				</description>
			</time>
			<time>
				02:31:30
				<tag>
					Vincent Racaniello, Ralph Baric, Statment
				</tag>
				<description>
					Sars 1 did not transmit until peak of discease, This transmit before symptoms.
				</description>
			</time>	
			<time>
				02:34:25
				<tag>
					Email, Vincent Racaniello
				</tag>
				<description>
					40% of people infected with SARS-CoV-2 have no symptoms
				</description>
			</time>	
			<time>
				02:35:15
				<tag>
					Email, Alan Dove
				</tag>
				<description>
					Bio Tech 3 Covid 19 projects
				</description>
			</time>	
			<time>
				02:37:17
				<tag>
					Rich Condit
				</tag>
				<description>
					8 Vaccines in clinical trials
				</description>
			</time>	
			<time>
				02:37:40
				<tag>
					Vincent Racaniello
				</tag>
				<description>
					If a fraction of the money spent now was spent preiviouly could have prevented this whole thing.
				</description>
			</time>	
			<time>
				02:40:00
				<tag>
					Rich Condit, Dickson Despommier
				</tag>
				<description>
					Increase with Covid 19 infections, New readers backgrounds
				</description>
			</time>	
		</meta>
	</episode>	
	<episode>
		627: Singapore National Centre for Infectious Diseases
		<meta>
			*
			<links>
				<link>
					*
				</link>
				<link>
					*
				</link>
				<link>
					*
				</link>
				<link>					
					*
				</link>
				<link>					
					*
				</link>
				<link>	
					*
				</link>
				<link>	
					*
				</link>
			</links>
			<time>
				00:00:00
				<tag>
					x 
				</tag>
				<description>
					x
				</description>
			</time>
		</meta>
	</episode>	
	<episode>
		628: Physical distance for COVID-19
		<meta>
			*
			<links>
				<link>
					*
				</link>
				<link>
					*
				</link>
				<link>
					*
				</link>
				<link>					
					*
				</link>
				<link>					
					*
				</link>
				<link>	
					*
				</link>
				<link>	
					*
				</link>
			</links>
			<time>
				00:00:00
				<tag>
					x 
				</tag>
				<description>
					x
				</description>
			</time>
		</meta>
	</eposode>	
	<episode>
		629: Coronavirus update, pandemic sitrep
		<meta>
			*
			<links>
				<link>
					*
				</link>
				<link>
					*
				</link>
				<link>
					*
				</link>
				<link>					
					*
				</link>
				<link>					
					*
				</link>
				<link>	
					*
				</link>
				<link>	
					*
				</link>
			</links>
			<time>
				00:00:00
				<tag>
					x 
				</tag>
				<description>
					x
				</description>
			</time>
		</meta>
	</episode>	
	<episode>
		630: Singapore Environmental Health Institute
		<meta>
			*
			<links>
				<link>
					*
				</link>
				<link>
					*
				</link>
				<link>
					*
				</link>
				<link>					
					*
				</link>
				<link>					
					*
				</link>
				<link>	
					*
				</link>
				<link>	
					*
				</link>
			</links>
			<time>
				00:00:00
				<tag>
					x 
				</tag>
				<description>
					x
				</description>
			</time>
		</meta>
	</episode>	
	<episode>
		631: Lots of eggs in the spike basket
		<meta>
			25062020, Vincent Racaniello, Rich Condit, Brianne Barker
			<links>
				<link>
					Paul Offit interview (Human Vaccines Proj) 4:03
				</link>
				<link>
					SARS-CoV-2 vaccine graphic (Milken Institute) 7:48
				</link>
				<link>
					Probability of symptoms and severe COVID-19 (aRxiv) 29:44
				</link>
				<link>					
					Cellular immune response without seroconversion (medRxiv) 10:09
				</link>
				<link>					
					Image credit
				</link>
				<link>	
					Letters read on TWiV 631 49:00
				</link>
			</links>
			<time>
				00:00:00
				<tag>
					x 
				</tag>
				<description>
					x
				</description>
			</time>
			<time>
				00:02:00
				<tag>
					x 
				</tag>
				<description>
					x
				</description>
			</time>			
			<time>
				00:03:00
				<tag>
					x 
				</tag>
				<description>
					x
				</description>
			</time>			
			<time>
				00:04:00
				<tag>
					x 
				</tag>
				<description>
					x
				</description>
			</time>			
			<time>
				00:07:00
				<tag>
					x 
				</tag>
				<description>
					x
				</description>
			</time>			
			<time>
				00:09:00
				<tag>
					x 
				</tag>
				<description>
					x
				</description>
			</time>			
			<time>
				00:10:00
				<tag>
					x 
				</tag>
				<description>
					x
				</description>
			</time>			
			<time>
				00:19:00
				<tag>
					x 
				</tag>
				<description>
					x
				</description>
			</time>			
			<time>
				00:21:00
				<tag>
					x 
				</tag>
				<description>
					x
				</description>
			</time>			
			<time>
				00:23:00
				<tag>
					x 
				</tag>
				<description>
					x
				</description>
			</time>			
			<time>
				00:24:00
				<tag>
					x 
				</tag>
				<description>
					x
				</description>
			</time>			
			<time>
				00:26:00
				<tag>
					x 
				</tag>
				<description>
					x
				</description>
			</time>			
			<time>
				00:28:00
				<tag>
					x 
				</tag>
				<description>
					x
				</description>
			</time>			
			<time>
				00:30:00
				<tag>
					x 
				</tag>
				<description>
					x
				</description>
			</time>			
			<time>
				00:41:00
				<tag>
					x 
				</tag>
				<description>
					x
				</description>
			</time>			
			<time>
				00:42:00
				<tag>
					x 
				</tag>
				<description>
					x
				</description>
			</time>			
			<time>
				00:43:00
				<tag>
					x 
				</tag>
				<description>
					x
				</description>
			</time>			
			<time>
				00:44:00
				<tag>
					x 
				</tag>
				<description>
					x
				</description>
			</time>			
			<time>
				00:45:00
				<tag>
					x 
				</tag>
				<description>
					x
				</description>
			</time>			
			<time>
				00:49:00
				<tag>
					x 
				</tag>
				<description>
					x
				</description>
			</time>			
			<time>
				00:51:00
				<tag>
					x 
				</tag>
				<description>
					x
				</description>
			</time>			
			<time>
				01:01:00
				<tag>
					x 
				</tag>
				<description>
					x
				</description>
			</time>			
			<time>
				01:07:00
				<tag>
					x 
				</tag>
				<description>
					x
				</description>
			</time>			
			<time>
				01:16:00
				<tag>
					x 
				</tag>
				<description>
					x
				</description>
			</time>			
			<time>
				01:18:00
				<tag>
					x 
				</tag>
				<description>
					x
				</description>
			</time>			
			<time>
				01:19:00
				<tag>
					x 
				</tag>
				<description>
					x
				</description>
			</time>			
			<time>
				01:22:00
				<tag>
					x 
				</tag>
				<description>
					x
				</description>
			</time>		
			<time>
				01:26:00
				<tag>
					x 
				</tag>
				<description>
					x
				</description>
			</time>		
			<time>
				01:31:00
				<tag>
					x 
				</tag>
				<description>
					x
				</description>
			</time>
			<time>
				01:35:00
				<tag>
					x 
				</tag>
				<description>
					x
				</description>
			</time>
			<time>
				01:36:00
				<tag>
					x 
				</tag>
				<description>
					x
				</description>
			</time>
			<time>
				01:41:00
				<tag>
					x 
				</tag>
				<description>
					x
				</description>
			</time>
			<time>
				01:45:00
				<tag>
					x 
				</tag>
				<description>
					x
				</description>
			</time>
			<time>
				01:52:00
				<tag>
					x 
				</tag>
				<description>
					x
				</description>
			</time>
			<time>
				01:55:00
				<tag>
					x 
				</tag>
				<description>
					x
				</description>
			</time>			
		</meta>		
	</episode>	
	<episode>
		632: Countering a miasma of anti-think
		<meta>
			 28062020, Vincent Racaniello, Dickson Despommier, Alan Dove, Kathy Spindler, Brianne Barker, Daniel Griffin, Chuck Knirsch
			<links>
				<link>
					Dexamethasone for COVID-19 (medRxiv) 11:40
				</link>
				<link>
					Proning trial for COVID-19 (Lancet) 10:59
				</link>
				<link>
					Tocilizumab for COVID-19 cytokine storm (Chest) 16:49
				</link>
				<link>					
					Global causes of death 41:07
				</link>
				<link>					
					Vesicular stomatitis in horses (ProMedMail) 53:34
				</link>
				<link>	
					Daily tests needed (Atlantic) 59:30
				</link>
				<link>	
					SARS-CoV-2 infection risks 1:44:53
				</link>
				<link>	
					Letters read on TWiV 632 30:51, 1:07:16
				</link>
			</links>
			<time>
				00:00:00
				<tag>
					x 
				</tag>
				<description>
					x
				</description>
			</time>
			<time>
				00:01:00
				<tag>
					x 
				</tag>
				<description>
					x
				</description>
			</time>			
			<time>
				00:03:00
				<tag>
					x 
				</tag>
				<description>
					x
				</description>
			</time>			
			<time>
				00:04:00
				<tag>
					x 
				</tag>
				<description>
					x
				</description>
			</time>			
			<time>
				00:05:00
				<tag>
					x 
				</tag>
				<description>
					x
				</description>
			</time>			
			<time>
				00:07:00
				<tag>
					x 
				</tag>
				<description>
					x
				</description>
			</time>			
			<time>
				00:12:00
				<tag>
					x 
				</tag>
				<description>
					x
				</description>
			</time>			
			<time>
				00:14:00
				<tag>
					x 
				</tag>
				<description>
					x
				</description>
			</time>			
			<time>
				00:15:00
				<tag>
					x 
				</tag>
				<description>
					x
				</description>
			</time>			
			<time>
				00:17:00
				<tag>
					x 
				</tag>
				<description>
					x
				</description>
			</time>			
			<time>
				00:20:00
				<tag>
					x 
				</tag>
				<description>
					x
				</description>
			</time>			
			<time>
				00:21:00
				<tag>
					x 
				</tag>
				<description>
					x
				</description>
			</time>			
			<time>
				00:23:00
				<tag>
					x 
				</tag>
				<description>
					x
				</description>
			</time>			
			<time>
				00:24:00
				<tag>
					x 
				</tag>
				<description>
					x
				</description>
			</time>				
			<time>
				00:26:00
				<tag>
					x 
				</tag>
				<description>
					x
				</description>
			</time>				
			<time>
				00:27:00
				<tag>
					x 
				</tag>
				<description>
					x
				</description>
			</time>						
			<time>
				00:30:00
				<tag>
					x 
				</tag>
				<description>
					x
				</description>
			</time>				
			<time>
				00:31:00
				<tag>
					x 
				</tag>
				<description>
					x
				</description>
			</time>				
			<time>
				00:34:00
				<tag>
					x 
				</tag>
				<description>
					x
				</description>
			</time>				
			<time>
				00:35:00
				<tag>
					x 
				</tag>
				<description>
					x
				</description>
			</time>				
			<time>
				00:38:00
				<tag>
					x 
				</tag>
				<description>
					x
				</description>
			</time>				
			<time>
				00:40:00
				<tag>
					x 
				</tag>
				<description>
					x
				</description>
			</time>				
			<time>
				00:41:00
				<tag>
					x 
				</tag>
				<description>
					x
				</description>
			</time>				
			<time>
				00:42:00
				<tag>
					x 
				</tag>
				<description>
					x
				</description>
			</time>				
			<time>
				00:43:00
				<tag>
					x 
				</tag>
				<description>
					x
				</description>
			</time>				
			<time>
				00:43:00
				<tag>
					x 
				</tag>
				<description>
					x
				</description>
			</time>				
			<time>
				00:44:00
				<tag>
					x 
				</tag>
				<description>
					x
				</description>
			</time>				
			<time>
				00:46:00
				<tag>
					x 
				</tag>
				<description>
					x
				</description>
			</time>				
		</meta>
	</episode>	
	<episode>
		633: Singapore viral
		<meta>
			12122019, 30062020, Vincent Racaniello, Sheemei Lok, Dahai Luo, Eng Eong Ooi, Ashley St. John
			<links>
				<link>
					Dengue virus and endothelial permeability (J Clin Invest) 25:04, 36:30
				</link>
				<link>
					Dengue virus morphological switch (PLoS Path) 49:27
				</link>
				<link>
					Symptomatic yellow fever vaccine infections (Nat Med) 1:03:28
				</link>
				<link>					
					RNA recognition by RIG-I and MDA5 (Nucl Acids Res) 1:17:34
				</link>
			</links>
			<time>
				00:00:00
				<tag>
					x 
				</tag>
				<description>
					x
				</description>
			</time>
			<time>
				00:06:00
				<tag>
					x 
				</tag>
				<description>
					x
				</description>
			</time>
			<time>
				00:10:00
				<tag>
					x 
				</tag>
				<description>
					x
				</description>
			</time>
			<time>
				00:13:00
				<tag>
					x 
				</tag>
				<description>
					x
				</description>
			</time>
			<time>
				00:15:00
				<tag>
					x 
				</tag>
				<description>
					x
				</description>
			</time>
			<time>
				00:17:00
				<tag>
					x 
				</tag>
				<description>
					x
				</description>
			</time>
			<time>
				00:17:00
				<tag>
					x 
				</tag>
				<description>
					x
				</description>
			</time>
			<time>
				00:20:00
				<tag>
					x 
				</tag>
				<description>
					x
				</description>
			</time>
			<time>
				00:24:00
				<tag>
					x 
				</tag>
				<description>
					x
				</description>
			</time>
			<time>
				00:26:00
				<tag>
					x 
				</tag>
				<description>
					x
				</description>
			</time>
			<time>
				00:29:00
				<tag>
					x 
				</tag>
				<description>
					x
				</description>
			</time>
			<time>
				00:30:00
				<tag>
					x 
				</tag>
				<description>
					x
				</description>
			</time>
			<time>
				00:32:00
				<tag>
					x 
				</tag>
				<description>
					x
				</description>
			</time>
			<time>
				00:35:00
				<tag>
					x 
				</tag>
				<description>
					x
				</description>
			</time>
			<time>
				00:38:00
				<tag>
					x 
				</tag>
				<description>
					x
				</description>
			</time>
			<time>
				00:40:00
				<tag>
					x 
				</tag>
				<description>
					x
				</description>
			</time>
			<time>
				00:41:00
				<tag>
					x 
				</tag>
				<description>
					x
				</description>
			</time>
			<time>
				00:44:00
				<tag>
					x 
				</tag>
				<description>
					x
				</description>
			</time>
			<time>
				00:46:00
				<tag>
					x 
				</tag>
				<description>
					x
				</description>
			</time>			
			<time>
				00:47:00
				<tag>
					x 
				</tag>
				<description>
					x
				</description>
			</time>			
			<time>
				00:49:00
				<tag>
					x 
				</tag>
				<description>
					x
				</description>
			</time>
			<time>
				00:52:00
				<tag>
					x 
				</tag>
				<description>
					x
				</description>
			</time>			
			<time>
				00:53:00
				<tag>
					x 
				</tag>
				<description>
					x
				</description>
			</time>			
			<time>
				00:55:00
				<tag>
					x 
				</tag>
				<description>
					x
				</description>
			</time>			
			<time>
				00:57:00
				<tag>
					x 
				</tag>
				<description>
					x
				</description>
			</time>			
			<time>
				00:59:00
				<tag>
					x 
				</tag>
				<description>
					x
				</description>
			</time>				
			<time>
				01:01:00
				<tag>
					x 
				</tag>
				<description>
					x
				</description>
			</time>			
			<time>
				01:03:00
				<tag>
					x 
				</tag>
				<description>
					x
				</description>
			</time>			
			<time>
				01:05:00
				<tag>
					x 
				</tag>
				<description>
					x
				</description>
			</time>			
			<time>
				01:07:00
				<tag>
					x 
				</tag>
				<description>
					x
				</description>
			</time>			
			<time>
				01:08:00
				<tag>
					x 
				</tag>
				<description>
					x
				</description>
			</time>			
			<time>
				01:10:00
				<tag>
					x 
				</tag>
				<description>
					x
				</description>
			</time>			
			<time>
				01:10:00
				<tag>
					x 
				</tag>
				<description>
					x
				</description>
			</time>			
			<time>
				01:12:00
				<tag>
					x 
				</tag>
				<description>
					x
				</description>
			</time>			
			<time>
				01:14:00
				<tag>
					x 
				</tag>
				<description>
					x
				</description>
			</time>			
			<time>
				01:16:00
				<tag>
					x 
				</tag>
				<description>
					x
				</description>
			</time>		
			<time>
				01:18:00
				<tag>
					x 
				</tag>
				<description>
					x
				</description>
			</time>
			<time>
				01:22:00
				<tag>
					x 
				</tag>
				<description>
					x
				</description>
			</time>
			<time>
				01:25:00
				<tag>
					x 
				</tag>
				<description>
					x
				</description>
			</time>
			<time>
				01:26:00
				<tag>
					x 
				</tag>
				<description>
					x
				</description>
			</time>
			<time>
				01:28:00
				<tag>
					x 
				</tag>
				<description>
					x
				</description>
			</time>
			<time>
				01:31:00
				<tag>
					x 
				</tag>
				<description>
					x
				</description>
			</time>		
		</meta>
	</episode>	
</podcast>
   